check_working/__init__.py
check_working/check_working.py
elbow_creator/__init__.py
elbow_creator/elbow_creator.py
elbow_creator-0.2.1.dist-info/METADATA
elbow_creator-0.2.1.dist-info/WHEEL
elbow_creator-0.2.1.dist-info/entry_points.txt
elbow_creator-0.2.1.dist-info/top_level.txt
elbow_creator-0.2.1.dist-info/RECORD
