Metadata-Version: 2.1
Name: elbow-creator
Version: 0.2.1
Summary: A package to create an elbow mesh in Blender
Home-page: https://github.com/VamshiGangadhar/elbow_creator
Author: Vamshi Gangadhar
Author-email: vamshi.gangadhar365@gmail.com
License: UNKNOWN
Platform: UNKNOWN
Requires-Dist: bpy
Requires-Dist: mathutils
